typenames/__init__.py
typenames/py.typed
typenames-2.1.0.dist-info/METADATA
typenames-2.1.0.dist-info/WHEEL
typenames-2.1.0.dist-info/licenses/LICENSE
typenames-2.1.0.dist-info/RECORD
