Metadata-Version: 2.4
Name: typenames
Version: 2.1.0
Summary: String representations of type annotations.
Project-URL: Homepage, https://typenames.drivendata.org/
Project-URL: Repository, https://github.com/drivendataorg/typenames
Project-URL: Documentation, https://typenames.drivendata.org/
Project-URL: Bug Tracker, https://github.com/drivendataorg/typenames/issues
Project-URL: Changelog, https://typenames.drivendata.org/stable/changelog/
Author-email: Jay Qi <jayqi.opensource@gmail.com>
License: MIT License
License-File: LICENSE
Keywords: pep 585,pep 604,type annotations,type hints,typing
Classifier: Intended Audience :: Developers
Classifier: License :: OSI Approved :: MIT License
Classifier: Operating System :: OS Independent
Classifier: Programming Language :: Python :: 3
Classifier: Programming Language :: Python :: 3.9
Classifier: Programming Language :: Python :: 3.10
Classifier: Programming Language :: Python :: 3.11
Classifier: Programming Language :: Python :: 3.12
Classifier: Programming Language :: Python :: 3.13
Classifier: Programming Language :: Python :: 3.14
Requires-Python: >=3.9
Provides-Extra: tests
Requires-Dist: pytest>=6; extra == 'tests'
